pixel_font_builder/__init__.py
pixel_font_builder/bdf/__init__.py
pixel_font_builder/bdf/common.py
pixel_font_builder/bdf/config.py
pixel_font_builder/builder.py
pixel_font_builder/glyph.py
pixel_font_builder/meta.py
pixel_font_builder/metric.py
pixel_font_builder/opentype/__init__.py
pixel_font_builder/opentype/common.py
pixel_font_builder/opentype/config.py
pixel_font_builder/opentype/feature.py
pixel_font_builder/opentype/name.py
pixel_font_builder/opentype/outline.py
pixel_font_builder/pcf/__init__.py
pixel_font_builder/pcf/common.py
pixel_font_builder/pcf/config.py
pixel_font_builder-0.0.47.dist-info/WHEEL
pixel_font_builder-0.0.47.dist-info/METADATA
pixel_font_builder-0.0.47.dist-info/RECORD
