Metadata-Version: 2.4
Name: pixel-font-builder
Version: 0.0.47
Summary: A library that helps create pixel style fonts
Keywords: font,pixel
Author: TakWolf
License-Expression: MIT
Classifier: Programming Language :: Python :: 3
Classifier: Programming Language :: Python :: 3.12
Classifier: Programming Language :: Python :: 3.13
Classifier: Programming Language :: Python :: 3.14
Classifier: License :: OSI Approved :: MIT License
Classifier: Operating System :: OS Independent
Requires-Dist: fonttools[woff]>=4.61.1
Requires-Dist: bdffont>=0.0.35
Requires-Dist: pcffont>=0.0.24
Maintainer: TakWolf
Requires-Python: >=3.12
Project-URL: Homepage, https://github.com/TakWolf/pixel-font-builder
Project-URL: Issues, https://github.com/TakWolf/pixel-font-builder/issues
Project-URL: Source, https://github.com/TakWolf/pixel-font-builder
